kinoko/__init__.py
kinoko/func.py
kinoko/misc/__init__.py
kinoko/misc/log_writer.py
kinoko/misc/web.py
kinoko/misc/network/__init__.py
kinoko/misc/network/chase_redirection.py
kinoko/misc/network/proxy.py
kinoko/misc/network/reachability.py
kinoko/sys/colormsg
kinoko/sys/vmem.sh
kinoko/text/__init__.py
kinoko/text/agg_tsv.py
kinoko/text/common.py
kinoko/text/io.py
kinoko/text/patch_tsv.py
kinoko-1.1.0.data/scripts/colormsg
kinoko-1.1.0.data/scripts/vmem.sh
tests/__init__.py
tests/test_common.py
tests/test_demo.py
tests/test_func.py
tests/test_network.py
tests/test_tsv.py
kinoko-1.1.0.dist-info/LICENSE
kinoko-1.1.0.dist-info/METADATA
kinoko-1.1.0.dist-info/WHEEL
kinoko-1.1.0.dist-info/entry_points.txt
kinoko-1.1.0.dist-info/top_level.txt
kinoko-1.1.0.dist-info/RECORD
