Metadata-Version: 2.1
Name: kinoko
Version: 1.1.0
Summary: python package for Japanese NLP and many other utils
Home-page: https://github.com/koyo922/kinoko
Author: qianweishuo
Author-email: qzy922@gmail.com
License: MIT
Keywords: NLP,japanese
Platform: UNKNOWN
Classifier: Programming Language :: Python
Classifier: Programming Language :: Python :: 2
Classifier: Programming Language :: Python :: 2.7
Classifier: Programming Language :: Python :: 3.6
Requires-Dist: arrow
Requires-Dist: codecov
Requires-Dist: docopt
Requires-Dist: lazy-property
Requires-Dist: pyfunctional
Requires-Dist: pytest
Requires-Dist: redo
Requires-Dist: requests
Requires-Dist: six
Requires-Dist: tqdm
Requires-Dist: pathlib2 ; python_version < "3.4"
Requires-Dist: typing ; python_version < "3.4"
Requires-Dist: tornado (<=4.4.2) ; python_version < "3.4"
Requires-Dist: tornado ; python_version >= "3.4"
